PyALE/_ALE_generic.py
PyALE/__init__.py
PyALE/_src/ALE_1D.py
PyALE/_src/ALE_2D.py
PyALE/_src/__init__.py
PyALE/_src/lib.py
tests/__init__.py
tests/test_1D_ale.py
tests/test_2D_ale.py
tests/test_ale.py
tests/test_lib.py
PyALE-1.2.0.dist-info/LICENSE
PyALE-1.2.0.dist-info/METADATA
PyALE-1.2.0.dist-info/WHEEL
PyALE-1.2.0.dist-info/top_level.txt
PyALE-1.2.0.dist-info/RECORD
