Metadata-Version: 2.1
Name: PyALE
Version: 1.2.0
Summary: ALE plots with python
Home-page: https://github.com/DanaJomar/PyALE
Author: Dana Jomar
Author-email: dana.jomar@outlook.com
Keywords: ALEPlots ALE feature effect interpretable ML
Classifier: Programming Language :: Python :: 3
Classifier: License :: OSI Approved :: MIT License
Classifier: Operating System :: OS Independent
License-File: LICENSE
Requires-Dist: numpy
Requires-Dist: pandas
Requires-Dist: matplotlib
Requires-Dist: scikit-learn
Requires-Dist: scipy
Requires-Dist: statsmodels
Provides-Extra: dev
Requires-Dist: coverage ; extra == 'dev'
